aiverify_fairness_metrics_toolbox_for_classification/__init__.py
aiverify_fairness_metrics_toolbox_for_classification/__main__.py
aiverify_fairness_metrics_toolbox_for_classification/algo.meta.json
aiverify_fairness_metrics_toolbox_for_classification/algo.py
aiverify_fairness_metrics_toolbox_for_classification/algo_init.py
aiverify_fairness_metrics_toolbox_for_classification/input.schema.json
aiverify_fairness_metrics_toolbox_for_classification/output.schema.json
aiverify_fairness_metrics_toolbox_for_classification/plugin_init.py
aiverify_fairness_metrics_toolbox_for_classification-2.1.0.dist-info/METADATA
aiverify_fairness_metrics_toolbox_for_classification-2.1.0.dist-info/WHEEL
aiverify_fairness_metrics_toolbox_for_classification-2.1.0.dist-info/entry_points.txt
aiverify_fairness_metrics_toolbox_for_classification-2.1.0.dist-info/licenses/AUTHORS.rst
aiverify_fairness_metrics_toolbox_for_classification-2.1.0.dist-info/licenses/LICENSE
aiverify_fairness_metrics_toolbox_for_classification-2.1.0.dist-info/licenses/NOTICE.md
aiverify_fairness_metrics_toolbox_for_classification-2.1.0.dist-info/RECORD
